{
  "lastUpdated": "2025-07-02T15:04:11.517Z",
  "totalParticipants": 2,
  "activeParticipants": 0,
  "recordHolders": 0,
  "weeklySuccessful": 2,
  "participants": [
    {
      "username": "tlqhrm",
      "avatarUrl": "https://avatars.githubusercontent.com/u/85216782?u=bb6b168d27265e788e395fbed052b64e691c556c&v=4",
      "lastPushed": "2025-07-02T14:59:16Z",
      "currentStreak": 2,
      "maxStreak": 2,
      "totalWeeks": 2,
      "successRate": 100,
      "currentWeekSuccess": true,
      "currentWeekCommits": 5
    },
    {
      "username": "wjstls123",
      "avatarUrl": "https://avatars.githubusercontent.com/u/218948587?v=4",
      "lastPushed": "2025-07-02T14:59:16Z",
      "currentStreak": 2,
      "maxStreak": 2,
      "totalWeeks": 2,
      "successRate": 100,
      "currentWeekSuccess": true,
      "currentWeekCommits": 2
    }
  ],
  "averageStreak": 2,
  "averageSuccessRate": 100,
  "rankingByStreak": [
    {
      "username": "tlqhrm",
      "avatarUrl": "https://avatars.githubusercontent.com/u/85216782?u=bb6b168d27265e788e395fbed052b64e691c556c&v=4",
      "lastPushed": "2025-07-02T14:59:16Z",
      "currentStreak": 2,
      "maxStreak": 2,
      "totalWeeks": 2,
      "successRate": 100,
      "currentWeekSuccess": true,
      "currentWeekCommits": 5
    },
    {
      "username": "wjstls123",
      "avatarUrl": "https://avatars.githubusercontent.com/u/218948587?v=4",
      "lastPushed": "2025-07-02T14:59:16Z",
      "currentStreak": 2,
      "maxStreak": 2,
      "totalWeeks": 2,
      "successRate": 100,
      "currentWeekSuccess": true,
      "currentWeekCommits": 2
    }
  ],
  "rankingBySuccessRate": [
    {
      "username": "tlqhrm",
      "avatarUrl": "https://avatars.githubusercontent.com/u/85216782?u=bb6b168d27265e788e395fbed052b64e691c556c&v=4",
      "lastPushed": "2025-07-02T14:59:16Z",
      "currentStreak": 2,
      "maxStreak": 2,
      "totalWeeks": 2,
      "successRate": 100,
      "currentWeekSuccess": true,
      "currentWeekCommits": 5
    },
    {
      "username": "wjstls123",
      "avatarUrl": "https://avatars.githubusercontent.com/u/218948587?v=4",
      "lastPushed": "2025-07-02T14:59:16Z",
      "currentStreak": 2,
      "maxStreak": 2,
      "totalWeeks": 2,
      "successRate": 100,
      "currentWeekSuccess": true,
      "currentWeekCommits": 2
    }
  ],
  "rankingByMaxStreak": [
    {
      "username": "tlqhrm",
      "avatarUrl": "https://avatars.githubusercontent.com/u/85216782?u=bb6b168d27265e788e395fbed052b64e691c556c&v=4",
      "lastPushed": "2025-07-02T14:59:16Z",
      "currentStreak": 2,
      "maxStreak": 2,
      "totalWeeks": 2,
      "successRate": 100,
      "currentWeekSuccess": true,
      "currentWeekCommits": 5
    },
    {
      "username": "wjstls123",
      "avatarUrl": "https://avatars.githubusercontent.com/u/218948587?v=4",
      "lastPushed": "2025-07-02T14:59:16Z",
      "currentStreak": 2,
      "maxStreak": 2,
      "totalWeeks": 2,
      "successRate": 100,
      "currentWeekSuccess": true,
      "currentWeekCommits": 2
    }
  ]
}